a_pandas_ex_lookupdict/LICENSE
a_pandas_ex_lookupdict/README.MD
a_pandas_ex_lookupdict/__init__.py
a_pandas_ex_lookupdict/requirements.txt
a_pandas_ex_lookupdict/thirdparty.json
a_pandas_ex_lookupdict-0.11.dist-info/LICENSE.rst
a_pandas_ex_lookupdict-0.11.dist-info/METADATA
a_pandas_ex_lookupdict-0.11.dist-info/WHEEL
a_pandas_ex_lookupdict-0.11.dist-info/top_level.txt
a_pandas_ex_lookupdict-0.11.dist-info/RECORD
